alogamous/__init__.py
alogamous/__main__.py
alogamous/__version__.py
alogamous/analyzer.py
alogamous/daily_count_analyzer.py
alogamous/daily_warning_analyzer.py
alogamous/directory_reader.py
alogamous/echo_analyzer.py
alogamous/error_counter_analyzer.py
alogamous/flag_duplicate_log_messages.py
alogamous/format_analyzer.py
alogamous/line_count_analyzer.py
alogamous/log_line_parser.py
alogamous/log_line_utility.py
alogamous/loginfo_analyzer.py
alogamous/peak_time_analyzer.py
alogamous/stack_trace_analyzer.py
alogamous/startup_header_analyzer.py
alogamous/warning_analyzer.py
alogamous-1.0.0.dist-info/METADATA
alogamous-1.0.0.dist-info/WHEEL
alogamous-1.0.0.dist-info/licenses/LICENSE.txt
alogamous-1.0.0.dist-info/RECORD
