Metadata-Version: 2.3
Name: alogamous
Version: 1.0.0
Summary: A log anomaly detection framework
Project-URL: Documentation, https://github.com/aquanauts/alogamous
Project-URL: Issues, https://github.com/aquanauts/alogamous/issues
Project-URL: Source, https://github.com/aquanauts/alogamous
License-Expression: MIT
License-File: LICENSE.txt
Classifier: Development Status :: 4 - Beta
Classifier: Programming Language :: Python
Classifier: Programming Language :: Python :: 3.8
Classifier: Programming Language :: Python :: 3.9
Classifier: Programming Language :: Python :: 3.10
Classifier: Programming Language :: Python :: 3.11
Classifier: Programming Language :: Python :: 3.12
Classifier: Programming Language :: Python :: Implementation :: CPython
Classifier: Programming Language :: Python :: Implementation :: PyPy
Requires-Python: >=3.8
Requires-Dist: pandas
